Metadata-Version: 2.1
Name: pyrobuf
Version: 0.9.2
Summary: A Cython based protobuf compiler
Home-page: https://github.com/appnexus/pyrobuf
Author: AppNexus
License: UNKNOWN
Platform: UNKNOWN
